odoo8_addon_resource_calendar_rrule-8.0.1.0.0-py2.7-nspkg.pth
odoo8_addon_resource_calendar_rrule-8.0.1.0.0.dist-info/DESCRIPTION.rst
odoo8_addon_resource_calendar_rrule-8.0.1.0.0.dist-info/METADATA
odoo8_addon_resource_calendar_rrule-8.0.1.0.0.dist-info/RECORD
odoo8_addon_resource_calendar_rrule-8.0.1.0.0.dist-info/WHEEL
odoo8_addon_resource_calendar_rrule-8.0.1.0.0.dist-info/metadata.json
odoo8_addon_resource_calendar_rrule-8.0.1.0.0.dist-info/namespace_packages.txt
odoo8_addon_resource_calendar_rrule-8.0.1.0.0.dist-info/top_level.txt
odoo_addons/resource_calendar_rrule/README.rst
odoo_addons/resource_calendar_rrule/__init__.py
odoo_addons/resource_calendar_rrule/__openerp__.py
odoo_addons/resource_calendar_rrule/models/__init__.py
odoo_addons/resource_calendar_rrule/models/resource_calendar.py
odoo_addons/resource_calendar_rrule/models/resource_calendar_attendance.py
odoo_addons/resource_calendar_rrule/security/res_groups.xml
odoo_addons/resource_calendar_rrule/static/description/icon.png
odoo_addons/resource_calendar_rrule/static/src/css/resource_calendar_rrule.css
odoo_addons/resource_calendar_rrule/static/src/js/resource_calendar_rrule.js
odoo_addons/resource_calendar_rrule/static/src/xml/resource_calendar_rrule.xml
odoo_addons/resource_calendar_rrule/tests/__init__.py
odoo_addons/resource_calendar_rrule/tests/test_resource_calendar_rrule.py
odoo_addons/resource_calendar_rrule/views/resource_calendar.xml
odoo_addons/resource_calendar_rrule/views/resource_calendar_attendance.xml
odoo_addons/resource_calendar_rrule/views/templates.xml
